odoo/addons/project_task_parent_completion_blocking/README.rst
odoo/addons/project_task_parent_completion_blocking/__init__.py
odoo/addons/project_task_parent_completion_blocking/__manifest__.py
odoo/addons/project_task_parent_completion_blocking/i18n/es.po
odoo/addons/project_task_parent_completion_blocking/i18n/it.po
odoo/addons/project_task_parent_completion_blocking/i18n/project_task_parent_completion_blocking.pot
odoo/addons/project_task_parent_completion_blocking/i18n/pt_BR.po
odoo/addons/project_task_parent_completion_blocking/models/__init__.py
odoo/addons/project_task_parent_completion_blocking/models/project_task.py
odoo/addons/project_task_parent_completion_blocking/readme/CONTRIBUTORS.md
odoo/addons/project_task_parent_completion_blocking/readme/DESCRIPTION.md
odoo/addons/project_task_parent_completion_blocking/static/description/icon.png
odoo/addons/project_task_parent_completion_blocking/static/description/index.html
odoo/addons/project_task_parent_completion_blocking/tests/__init__.py
odoo/addons/project_task_parent_completion_blocking/tests/test_project_task_parent_completion_blocking.py
odoo_addon_project_task_parent_completion_blocking-18.0.1.0.0.5.dist-info/METADATA
odoo_addon_project_task_parent_completion_blocking-18.0.1.0.0.5.dist-info/WHEEL
odoo_addon_project_task_parent_completion_blocking-18.0.1.0.0.5.dist-info/top_level.txt
odoo_addon_project_task_parent_completion_blocking-18.0.1.0.0.5.dist-info/RECORD
